{
  "biomedicalConceptId": "BiomedicalConcept_200",
  "bcName": "Interleukin 6 Measurement",
  "bcSynonyms": [
    "INTLK6",
    "Interleukin 6"
  ],
  "bcReference": "/mdr/bc/packages/2023-03-31/biomedicalconcepts/C74834",
  "bcProperties": [
    {
      "bcPropertyId": "BiomedicalConceptProperty_648",
      "bcPropertyName": "Laboratory Test Result",
      "bcPropertyRequired": true,
      "bcPropertyEnabled": true,
      "bcPropertyDatatype": "decimal",
      "bcPropertyResponseCodes": [],
      "bcPropertyConceptCode": {
        "aliasCodeId": "AliasCode_848",
        "standardCode": {
          "codeId": "Code_894",
          "code": "C36292",
          "codeSystem": "NCI Thesaurus",
          "codeSystemVersion": "",
          "decode": "Laboratory Test Result"
        },
        "standardCodeAliases": []
      }
    },
    {
      "bcPropertyId": "BiomedicalConceptProperty_649",
      "bcPropertyName": "Unit of Arbitrary or Mass Concentration",
      "bcPropertyRequired": true,
      "bcPropertyEnabled": true,
      "bcPropertyDatatype": "string",
      "bcPropertyResponseCodes": [],
      "bcPropertyConceptCode": {
        "aliasCodeId": "AliasCode_849",
        "standardCode": {
          "codeId": "Code_895",
          "code": "NEW_6",
          "codeSystem": "NCI Thesaurus",
          "codeSystemVersion": "",
          "decode": "Unit of Arbitrary or Mass Concentration"
        },
        "standardCodeAliases": []
      }
    },
    {
      "bcPropertyId": "BiomedicalConceptProperty_650",
      "bcPropertyName": "Biospecimen Type",
      "bcPropertyRequired": true,
      "bcPropertyEnabled": true,
      "bcPropertyDatatype": "string",
      "bcPropertyResponseCodes": [],
      "bcPropertyConceptCode": {
        "aliasCodeId": "AliasCode_850",
        "standardCode": {
          "codeId": "Code_896",
          "code": "C70713",
          "codeSystem": "NCI Thesaurus",
          "codeSystemVersion": "",
          "decode": "Biospecimen Type"
        },
        "standardCodeAliases": []
      }
    }
  ],
  "bcConceptCode": {
    "aliasCodeId": "AliasCode_847",
    "standardCode": {
      "codeId": "Code_893",
      "code": "C74834",
      "codeSystem": "NCI Thesaurus",
      "codeSystemVersion": "",
      "decode": "Interleukin 6 Measurement"
    },
    "standardCodeAliases": []
  }
}